pdf_text_overlay/__init__.py
pdf_text_overlay/pdfWriter.py
pdf_text_overlay-0.4.4.dist-info/licenses/LICENSE
pdf_text_overlay-0.4.4.dist-info/METADATA
pdf_text_overlay-0.4.4.dist-info/WHEEL
pdf_text_overlay-0.4.4.dist-info/top_level.txt
pdf_text_overlay-0.4.4.dist-info/RECORD
